ds_core_sanpi/__init__.py
ds_core_sanpi/classifier_utils.py
ds_core_sanpi/exploratory_data_analyzer.py
ds_core_sanpi/regressor_utils.py
ds_core_sanpier-0.1.4.data/scripts/classifier_utils.py
ds_core_sanpier-0.1.4.data/scripts/exploratory_data_analyzer.py
ds_core_sanpier-0.1.4.data/scripts/regressor_utils.py
ds_core_sanpier-0.1.4.dist-info/LICENSE.txt
ds_core_sanpier-0.1.4.dist-info/METADATA
ds_core_sanpier-0.1.4.dist-info/WHEEL
ds_core_sanpier-0.1.4.dist-info/top_level.txt
ds_core_sanpier-0.1.4.dist-info/RECORD
