Metadata-Version: 2.1
Name: ds-core-sanpier
Version: 0.1.4
Summary: A package to automize some of the steps before modeling and in the modeling stage
Home-page: http://pypi.python.org/pypi/ds-core-sanpier/
Author: Saner Turhaner
Author-email: san-pi@windowslive.com
License: MIT
Project-URL: Bug Tracker, http://pypi.python.org/pypi/ds-core-sanpier/issues
Classifier: License :: OSI Approved :: MIT License
Classifier: Operating System :: OS Independent
Classifier: Programming Language :: Python :: 3
Classifier: Programming Language :: Python :: 3.6
Requires-Python: >=3.6
License-File: LICENSE.txt
Requires-Dist: catboost (>=1.0.5)
Requires-Dist: imblearn (>=0.0)
Requires-Dist: lightgbm (>=3.3.2)
Requires-Dist: lofo-importance (>=0.3.1)
Requires-Dist: matplotlib (>=3.3.4)
Requires-Dist: numpy (>=1.19.5)
Requires-Dist: pandas (>=1.1.5)
Requires-Dist: seaborn (>=0.11.1)
Requires-Dist: scikit-learn (>=0.24.2)
Requires-Dist: shap (>=0.40.0)
